pawapi/__init__.py
pawapi/client.py
pawapi/exceptions.py
pawapi/interval.py
pawapi/pawapi.py
pawapi/py.typed
pawapi/python.py
pawapi/region.py
pawapi/shell.py
pawapi/system.py
pawapi/utils.py
pawapi/version.py
pawapi/api/__init__.py
pawapi/api/_types.py
pawapi/api/base.py
pawapi/api/console.py
pawapi/api/cpu.py
pawapi/api/file.py
pawapi/api/python.py
pawapi/api/students.py
pawapi/api/system.py
pawapi/api/task.py
pawapi/api/webapp.py
pypawapi-2.0.0.dist-info/METADATA
pypawapi-2.0.0.dist-info/WHEEL
pypawapi-2.0.0.dist-info/licenses/LICENSE
pypawapi-2.0.0.dist-info/RECORD
