Metadata-Version: 2.1
Name: pypawapi
Version: 2.0.0
Summary: API wrapper for pythonanywhere
Project-URL: Source, https://codeberg.org/maraudeur/pawapi
Author-email: Maraudeur <maraudeur1@protonmail.ch>
License:  The MIT License (MIT)
License-File: LICENSE
Keywords: api,paw,pawapi,pythonanywhere
Classifier: License :: OSI Approved :: MIT License
Classifier: Programming Language :: Python
Classifier: Programming Language :: Python :: 3
Classifier: Programming Language :: Python :: 3 :: Only
Classifier: Programming Language :: Python :: 3.7
Classifier: Programming Language :: Python :: 3.8
Classifier: Programming Language :: Python :: 3.9
Classifier: Programming Language :: Python :: 3.10
Classifier: Programming Language :: Python :: 3.11
Classifier: Typing :: Typed
Requires-Python: >=3.7
Requires-Dist: requests<3.0.0,>=2.22.0
Provides-Extra: dev
Requires-Dist: pre-commit<3.0.0,>=2.0.0; extra == 'dev'
Provides-Extra: lint
Requires-Dist: flake8-bugbear==22.6.22; extra == 'lint'
Requires-Dist: flake8<6.0.0,>=5.0.0; extra == 'lint'
Requires-Dist: isort<6.0.0,>=5.10.1; extra == 'lint'
Requires-Dist: mypy<1.0.0,>=0.960; extra == 'lint'
Requires-Dist: toml==0.10.2; extra == 'lint'
Requires-Dist: types-requests; extra == 'lint'
Requires-Dist: yapf==0.32.0; extra == 'lint'
Provides-Extra: test
Requires-Dist: coverage<7.0.0,>=6.0.0; extra == 'test'
Requires-Dist: pytest-cov<5.0.0,>=4.0.0; extra == 'test'
Requires-Dist: pytest<8.0.0,>=7.0.0; extra == 'test'
Requires-Dist: responses<1.0.0,>=0.21.0; extra == 'test'
